YLTK/__init__.py
YLTK/main.py
YLTK/yltk.py
yltk-0.1.1.dist-info/LICENSE
yltk-0.1.1.dist-info/METADATA
yltk-0.1.1.dist-info/WHEEL
yltk-0.1.1.dist-info/top_level.txt
yltk-0.1.1.dist-info/RECORD
