Metadata-Version: 2.1
Name: yltk
Version: 0.1.1
Summary: ---
Home-page: https://github.com/atanseiye/YLTK-library
Author: Kolade Atanseiye
Author-email: kolade.atanseiye@outlook.com
Classifier: Programming Language :: Python :: 3
Classifier: License :: OSI Approved :: MIT License
Classifier: Operating System :: OS Independent
License-File: LICENSE
Requires-Dist: openai
